{
    "text": " Este es el vaso de la presa te\u00f1ita, est\u00e1 completamente lleno. Esa agua es la que se est\u00e1 soltando para que no reviente la presa. Lo estamos haciendo con mucho f\u00e9culo, con cuidado, para no soltar m\u00e1s agua. Y agarrar m\u00e1s la inundaci\u00f3n en la planicie de la vasco. Este es el r\u00edo Samaria. Este es la cortina. El problema que tenemos es que llueve mucho en esta parte de la presa hacia arriba. Estamos en el estado de Chiapas. Hay cuatro presas, la Bustura, Chihuahua, el Vaso y esta que es la \u00faltima ya para la planicie del estado. Esta es la cortina de la presa. Miren c\u00f3mo est\u00e1. Y este es el Catefobre. Y ahora vamos a 1800 metros p\u00fablicos al segundo. Porque est\u00e1 200 metros.",
    "segments": [
        {
            "id": 0,
            "seek": 0,
            "start": 0.0,
            "end": 7.0,
            "text": " Este es el vaso de la presa te\u00f1ita, est\u00e1 completamente lleno.",
            "tokens": [
                50364,
                16105,
                785,
                806,
                11481,
                78,
                368,
                635,
                1183,
                64,
                535,
                2791,
                2786,
                11,
                3192,
                28381,
                4849,
                5808,
                13,
                50714
            ],
            "temperature": 0.0,
            "avg_logprob": -0.28763052821159363,
            "compression_ratio": 1.4217687074829932,
            "no_speech_prob": 0.5871699452400208
        },
        {
            "id": 1,
            "seek": 0,
            "start": 9.0,
            "end": 19.0,
            "text": " Esa agua es la que se est\u00e1 soltando para que no reviente la presa.",
            "tokens": [
                50814,
                2313,
                64,
                19330,
                785,
                635,
                631,
                369,
                3192,
                1404,
                83,
                1806,
                1690,
                631,
                572,
                3698,
                8413,
                635,
                1183,
                64,
                13,
                51314
            ],
            "temperature": 0.0,
            "avg_logprob": -0.28763052821159363,
            "compression_ratio": 1.4217687074829932,
            "no_speech_prob": 0.5871699452400208
        },
        {
            "id": 2,
            "seek": 0,
            "start": 20.0,
            "end": 28.0,
            "text": " Lo estamos haciendo con mucho f\u00e9culo, con cuidado, para no soltar m\u00e1s agua.",
            "tokens": [
                51364,
                6130,
                10382,
                20509,
                416,
                9824,
                34271,
                25436,
                11,
                416,
                31891,
                11,
                1690,
                572,
                1404,
                23480,
                3573,
                19330,
                13,
                51764
            ],
            "temperature": 0.0,
            "avg_logprob": -0.28763052821159363,
            "compression_ratio": 1.4217687074829932,
            "no_speech_prob": 0.5871699452400208
        },
        {
            "id": 3,
            "seek": 2800,
            "start": 28.0,
            "end": 35.0,
            "text": " Y agarrar m\u00e1s la inundaci\u00f3n en la planicie de la vasco.",
            "tokens": [
                50364,
                398,
                623,
                2284,
                289,
                3573,
                635,
                294,
                997,
                3482,
                465,
                635,
                1393,
                28434,
                368,
                635,
                11481,
                1291,
                13,
                50714
            ],
            "temperature": 0.0,
            "avg_logprob": -0.3904776939978966,
            "compression_ratio": 1.120879120879121,
            "no_speech_prob": 0.05377654358744621
        },
        {
            "id": 4,
            "seek": 2800,
            "start": 40.0,
            "end": 43.0,
            "text": " Este es el r\u00edo Samaria.",
            "tokens": [
                50964,
                16105,
                785,
                806,
                367,
                20492,
                4832,
                9831,
                13,
                51114
            ],
            "temperature": 0.0,
            "avg_logprob": -0.3904776939978966,
            "compression_ratio": 1.120879120879121,
            "no_speech_prob": 0.05377654358744621
        },
        {
            "id": 5,
            "seek": 2800,
            "start": 47.0,
            "end": 49.0,
            "text": " Este es la cortina.",
            "tokens": [
                51314,
                16105,
                785,
                635,
                11278,
                1426,
                13,
                51414
            ],
            "temperature": 0.0,
            "avg_logprob": -0.3904776939978966,
            "compression_ratio": 1.120879120879121,
            "no_speech_prob": 0.05377654358744621
        },
        {
            "id": 6,
            "seek": 5800,
            "start": 58.0,
            "end": 69.0,
            "text": " El problema que tenemos es que llueve mucho en esta parte de la presa hacia arriba.",
            "tokens": [
                50364,
                2699,
                12395,
                631,
                9914,
                785,
                631,
                4849,
                622,
                303,
                9824,
                465,
                5283,
                6975,
                368,
                635,
                1183,
                64,
                21365,
                28469,
                13,
                50914
            ],
            "temperature": 0.0,
            "avg_logprob": -0.2790859446806066,
            "compression_ratio": 1.4387096774193548,
            "no_speech_prob": 0.0942435935139656
        },
        {
            "id": 7,
            "seek": 5800,
            "start": 70.0,
            "end": 72.0,
            "text": " Estamos en el estado de Chiapas.",
            "tokens": [
                50964,
                34563,
                465,
                806,
                18372,
                368,
                17730,
                569,
                296,
                13,
                51064
            ],
            "temperature": 0.0,
            "avg_logprob": -0.2790859446806066,
            "compression_ratio": 1.4387096774193548,
            "no_speech_prob": 0.0942435935139656
        },
        {
            "id": 8,
            "seek": 5800,
            "start": 73.0,
            "end": 86.0,
            "text": " Hay cuatro presas, la Bustura, Chihuahua, el Vaso y esta que es la \u00faltima ya para la planicie del estado.",
            "tokens": [
                51114,
                8721,
                28795,
                1183,
                296,
                11,
                635,
                363,
                381,
                2991,
                11,
                761,
                44344,
                545,
                4398,
                11,
                806,
                23299,
                78,
                288,
                5283,
                631,
                785,
                635,
                28118,
                2478,
                1690,
                635,
                1393,
                28434,
                1103,
                18372,
                13,
                51764
            ],
            "temperature": 0.0,
            "avg_logprob": -0.2790859446806066,
            "compression_ratio": 1.4387096774193548,
            "no_speech_prob": 0.0942435935139656
        },
        {
            "id": 9,
            "seek": 8800,
            "start": 88.0,
            "end": 91.0,
            "text": " Esta es la cortina de la presa.",
            "tokens": [
                50364,
                20547,
                785,
                635,
                11278,
                1426,
                368,
                635,
                1183,
                64,
                13,
                50514
            ],
            "temperature": 0.0,
            "avg_logprob": -0.33714470656021783,
            "compression_ratio": 1.1071428571428572,
            "no_speech_prob": 0.022554755210876465
        },
        {
            "id": 10,
            "seek": 8800,
            "start": 92.0,
            "end": 94.0,
            "text": " Miren c\u00f3mo est\u00e1.",
            "tokens": [
                50564,
                376,
                18833,
                12826,
                3192,
                13,
                50664
            ],
            "temperature": 0.0,
            "avg_logprob": -0.33714470656021783,
            "compression_ratio": 1.1071428571428572,
            "no_speech_prob": 0.022554755210876465
        },
        {
            "id": 11,
            "seek": 8800,
            "start": 98.0,
            "end": 100.0,
            "text": " Y este es el Catefobre.",
            "tokens": [
                50864,
                398,
                4065,
                785,
                806,
                383,
                473,
                69,
                996,
                265,
                13,
                50964
            ],
            "temperature": 0.0,
            "avg_logprob": -0.33714470656021783,
            "compression_ratio": 1.1071428571428572,
            "no_speech_prob": 0.022554755210876465
        },
        {
            "id": 12,
            "seek": 8800,
            "start": 106.0,
            "end": 113.0,
            "text": " Y ahora vamos a 1800 metros p\u00fablicos al segundo.",
            "tokens": [
                51264,
                398,
                9923,
                5295,
                257,
                24327,
                34761,
                15392,
                329,
                419,
                17954,
                13,
                51614
            ],
            "temperature": 0.0,
            "avg_logprob": -0.33714470656021783,
            "compression_ratio": 1.1071428571428572,
            "no_speech_prob": 0.022554755210876465
        },
        {
            "id": 13,
            "seek": 11300,
            "start": 113.0,
            "end": 119.0,
            "text": " Porque est\u00e1 200 metros.",
            "tokens": [
                50414,
                11287,
                3192,
                2331,
                34761,
                13,
                50664
            ],
            "temperature": 0.0,
            "avg_logprob": -0.4399409890174866,
            "compression_ratio": 0.75,
            "no_speech_prob": 0.10889916867017746
        }
    ],
    "language": "es"
}