{
    "video_id": "FMfAukaIrQE",
    "video_thumbnail_url": "https://i.ytimg.com/vi/FMfAukaIrQE/hqdefault.jpg?sqp=-oaymwEcCNACELwBSFXyq4qpAw4IARUAAIhCGAFwAcABBg==&rs=AOn4CLD_5zaNm-xyD3B4KAk2SBhkdWUVpQ",
    "video_url": "https://www.youtube.com/watch?v=FMfAukaIrQE",
    "video_title": "AMLO sobre detenci\u00f3n de Duarte",
    "video_length_seconds": 457,
    "transcription_with_timestamps": [
        {
            "text": "la semana santa fue como la semana de",
            "start": 1.16,
            "duration": 6.779
        },
        {
            "text": "los curas de la pol\u00edtica mexicana el",
            "start": 3.71,
            "duration": 8.07
        },
        {
            "text": "caso m\u00e1s sonado fue sin duda el de la",
            "start": 7.939,
            "duration": 5.58
        },
        {
            "text": "detenci\u00f3n de parte del gobernador",
            "start": 11.78,
            "duration": 7.38
        },
        {
            "text": "corrupto de veracruz la gente sabe",
            "start": 13.519,
            "duration": 9.141
        },
        {
            "text": "porque estuvieron",
            "start": 19.16,
            "duration": 6.98
        },
        {
            "text": "es yo pienso de dominio p\u00fablico de todas",
            "start": 22.66,
            "duration": 7.23
        },
        {
            "text": "maneras es importante dar a conocer",
            "start": 26.14,
            "duration": 5.149
        },
        {
            "text": "nuestro",
            "start": 29.89,
            "duration": 3.439
        },
        {
            "text": "punto de vista",
            "start": 31.289,
            "duration": 4.101
        },
        {
            "text": "nuestra versi\u00f3n",
            "start": 33.329,
            "duration": 5.811
        },
        {
            "text": "pensamos igual que la gente que es una",
            "start": 35.39,
            "duration": 5.24
        },
        {
            "text": "maniobra",
            "start": 39.14,
            "duration": 5.89
        },
        {
            "text": "pol\u00edtica porque hay elecciones en puerta",
            "start": 40.63,
            "duration": 6.63
        },
        {
            "text": "tanto en veracruz como mil estado de",
            "start": 45.03,
            "duration": 6.549
        },
        {
            "text": "m\u00e9xico y est\u00e1n muy nerviosos",
            "start": 47.26,
            "duration": 8.64
        },
        {
            "text": "est\u00e1 cayendo spri est\u00e1 cayendo el pan",
            "start": 51.579,
            "duration": 10.891
        },
        {
            "text": "los dos partes que son los que est\u00e1n en",
            "start": 55.9,
            "duration": 10.25
        },
        {
            "text": "picada y morena est\u00e1 creciendo mucho",
            "start": 62.47,
            "duration": 5.9
        },
        {
            "text": "entonces",
            "start": 66.15,
            "duration": 5.4
        },
        {
            "text": "y tomaron la decisi\u00f3n de detener en",
            "start": 68.37,
            "duration": 6.9
        },
        {
            "text": "estos momentos a duarte para",
            "start": 71.55,
            "duration": 7.08
        },
        {
            "text": "buscas en lo das",
            "start": 75.27,
            "duration": 5.23
        },
        {
            "text": "a morir",
            "start": 78.63,
            "duration": 5.05
        },
        {
            "text": "hay que tener en cuenta que y\u00fanes",
            "start": 80.5,
            "duration": 6.66
        },
        {
            "text": "linares gobernador tambi\u00e9n corrupto de",
            "start": 83.68,
            "duration": 6.39
        },
        {
            "text": "veracruz llev\u00f3 a declarar de que",
            "start": 87.16,
            "duration": 5.88
        },
        {
            "text": "nosotros proteg\u00edamos a duarte porque",
            "start": 90.07,
            "duration": 4.83
        },
        {
            "text": "duarte le daba dinero a morenico su",
            "start": 93.04,
            "duration": 6.119
        },
        {
            "text": "prima de dinero a m\u00ed nada",
            "start": 94.9,
            "duration": 6.779
        },
        {
            "text": "ha podido probar porque desde luego que",
            "start": 99.159,
            "duration": 5.731
        },
        {
            "text": "no es cierto pero aplica la m\u00e1xima",
            "start": 101.679,
            "duration": 6.12
        },
        {
            "text": "adelantada de la pol\u00edtica seg\u00fan la cual",
            "start": 104.89,
            "duration": 7.35
        },
        {
            "text": "la calumnia cuando no mancha tista y",
            "start": 107.799,
            "duration": 8.191
        },
        {
            "text": "ahora detienen a duarte en estos",
            "start": 112.24,
            "duration": 7.95
        },
        {
            "text": "momentos y sale a declarar",
            "start": 115.99,
            "duration": 7.61
        },
        {
            "text": "y\u00fanes el primero",
            "start": 120.19,
            "duration": 6.71
        },
        {
            "text": "dice que ya cumpli\u00f3 con la detenci\u00f3n de",
            "start": 123.6,
            "duration": 6.03
        },
        {
            "text": "suerte porque piensa que con eso se va a",
            "start": 126.9,
            "duration": 6.69
        },
        {
            "text": "fortalecer \u00e9l y el pan en veracruz pero",
            "start": 129.63,
            "duration": 6.45
        },
        {
            "text": "por cierto est\u00e1 apoyando a su hijo como",
            "start": 133.59,
            "duration": 4.75
        },
        {
            "text": "candidato a presidente municipal",
            "start": 136.08,
            "duration": 5.41
        },
        {
            "text": "del puerto de veracruz por el pan",
            "start": 138.34,
            "duration": 5.7
        },
        {
            "text": "no les va a funcionar nada les sale",
            "start": 141.49,
            "duration": 5.37
        },
        {
            "text": "tambi\u00e9n a decir y\u00fanes que felicitaba a",
            "start": 144.04,
            "duration": 5.22
        },
        {
            "text": "pe\u00f1a nieto por la detenci\u00f3n de suerte",
            "start": 146.86,
            "duration": 6.27
        },
        {
            "text": "pero lo m\u00e1s interesante es que declara",
            "start": 149.26,
            "duration": 7.35
        },
        {
            "text": "ayer josefina v\u00e1zquez mota que ahora que",
            "start": 153.13,
            "duration": 6.99
        },
        {
            "text": "le tienen a duarte debe d",
            "start": 156.61,
            "duration": 7.079
        },
        {
            "text": "declarado arte sobre el dinero que",
            "start": 160.12,
            "duration": 6.68
        },
        {
            "text": "entregaba a morena",
            "start": 163.689,
            "duration": 8.051
        },
        {
            "text": "es decir lleva ese prop\u00f3sito de",
            "start": 166.8,
            "duration": 7.76
        },
        {
            "text": "perjudicar a morena de enlodar a morir",
            "start": 171.74,
            "duration": 6.16
        },
        {
            "text": "con la detenci\u00f3n de \u00e9dgar nosotros no",
            "start": 174.56,
            "duration": 5.62
        },
        {
            "text": "tenemos ninguna relaci\u00f3n con duarte ni",
            "start": 177.9,
            "duration": 4.44
        },
        {
            "text": "con ning\u00fan corrupto",
            "start": 180.18,
            "duration": 5.29
        },
        {
            "text": "y ella no tiene las",
            "start": 182.34,
            "duration": 6.48
        },
        {
            "text": "josefina v\u00e1squez mota",
            "start": 185.47,
            "duration": 3.35
        },
        {
            "text": "moral",
            "start": 189.17,
            "duration": 3.2
        },
        {
            "text": "ella",
            "start": 190.819,
            "duration": 6.53
        },
        {
            "text": "recibi\u00f3 y est\u00e1 probado eso s\u00ed est\u00e1",
            "start": 192.37,
            "duration": 8.67
        },
        {
            "text": "demostrado no la calumnia de que duarte",
            "start": 197.349,
            "duration": 6.071
        },
        {
            "text": "le da dinero",
            "start": 201.04,
            "duration": 7.0
        },
        {
            "text": "a morena lo que s\u00ed se comprob\u00f3 es que",
            "start": 203.42,
            "duration": 8.039
        },
        {
            "text": "despu\u00e9s de la elecci\u00f3n del 2012 que ya",
            "start": 208.04,
            "duration": 8.3
        },
        {
            "text": "fue candidata sus defina las que no est\u00e1",
            "start": 211.459,
            "duration": 4.881
        },
        {
            "text": "presidenta de la rep\u00fablica por el pan",
            "start": 216.81,
            "duration": 5.29
        },
        {
            "text": "y pasan las elecciones del 2012 y",
            "start": 219.97,
            "duration": 7.27
        },
        {
            "text": "desaparece y se sabe qu\u00e9",
            "start": 222.1,
            "duration": 8.29
        },
        {
            "text": "pe\u00f1a nieto autor y son despu\u00e9s de la",
            "start": 227.24,
            "duration": 6.27
        },
        {
            "text": "elecci\u00f3n del 2012 que le entregar\u00e1n a",
            "start": 230.39,
            "duration": 5.55
        },
        {
            "text": "josefina v\u00e1zquez mota del presupuesto",
            "start": 233.51,
            "duration": 4.98
        },
        {
            "text": "p\u00fablico m\u00e1s de mil millones de pesos",
            "start": 235.94,
            "duration": 4.42
        },
        {
            "text": "para su fundaci\u00f3n",
            "start": 238.49,
            "duration": 4.65
        },
        {
            "text": "supuestamente para apoyar a migrantes",
            "start": 240.36,
            "duration": 6.9
        },
        {
            "text": "nunca ha demostrado que utiliz\u00f3 lo",
            "start": 243.14,
            "duration": 6.43
        },
        {
            "text": "cierto aunque suene fuerte y luego con",
            "start": 247.26,
            "duration": 5.18
        },
        {
            "text": "respeto es que se vendi\u00f3",
            "start": 249.57,
            "duration": 7.13
        },
        {
            "text": "pero s\u00f3lo es ellos tienen arreglo",
            "start": 252.44,
            "duration": 7.68
        },
        {
            "text": "la c\u00fapula por eso hablo del prian y",
            "start": 256.7,
            "duration": 6.48
        },
        {
            "text": "siempre he sostenido que son lo mismo",
            "start": 260.12,
            "duration": 5.03
        },
        {
            "text": "iguales de",
            "start": 263.18,
            "duration": 5.63
        },
        {
            "text": "los del pri los del pan de arriba hace",
            "start": 265.15,
            "duration": 5.96
        },
        {
            "text": "dos meses",
            "start": 268.81,
            "duration": 4.759
        },
        {
            "text": "y dio a conocer",
            "start": 271.11,
            "duration": 5.1
        },
        {
            "text": "en una columna del peri\u00f3dico universal",
            "start": 273.569,
            "duration": 7.31
        },
        {
            "text": "que se reunieron a medianoche anaya",
            "start": 276.21,
            "duration": 7.879
        },
        {
            "text": "presidente del pan un aprendiz de",
            "start": 280.879,
            "duration": 6.211
        },
        {
            "text": "mafioso con pe\u00f1a nieto",
            "start": 284.089,
            "duration": 6.04
        },
        {
            "text": "tambi\u00e9n de la noche los pinos",
            "start": 287.09,
            "duration": 6.639
        },
        {
            "text": "y hay la versi\u00f3n de que a esa reuni\u00f3n",
            "start": 290.129,
            "duration": 7.31
        },
        {
            "text": "asisti\u00f3 tambi\u00e9n y ah\u00ed tomaron el acuerdo",
            "start": 293.729,
            "duration": 7.96
        },
        {
            "text": "de ir juntos de facto",
            "start": 297.439,
            "duration": 7.28
        },
        {
            "text": "de hecho en el estado de m\u00e9xico con dos",
            "start": 301.689,
            "duration": 6.21
        },
        {
            "text": "candidaturas las dem\u00e1s del pri y la de",
            "start": 304.719,
            "duration": 5.901
        },
        {
            "text": "josefina v\u00e1squez mota",
            "start": 307.899,
            "duration": 4.571
        },
        {
            "text": "para enfrentar",
            "start": 310.62,
            "duration": 6.17
        },
        {
            "text": "a morena ahora que morena est\u00e1 arriba en",
            "start": 312.47,
            "duration": 7.92
        },
        {
            "text": "veracruz arriba en el estado de m\u00e9xico",
            "start": 316.79,
            "duration": 7.83
        },
        {
            "text": "est\u00e1n muy desesperados y est\u00e1n con esta",
            "start": 320.39,
            "duration": 6.3
        },
        {
            "text": "treta",
            "start": 324.62,
            "duration": 6.25
        },
        {
            "text": "buscando frenar la morena no lo van a",
            "start": 326.69,
            "duration": 5.49
        },
        {
            "text": "lograr",
            "start": 330.87,
            "duration": 4.4
        },
        {
            "text": "ahora que tienen a duarte amigos",
            "start": 332.18,
            "duration": 5.94
        },
        {
            "text": "nuestros de las redes sociales empiezan",
            "start": 335.27,
            "duration": 5.51
        },
        {
            "text": "a preocuparse",
            "start": 338.12,
            "duration": 2.66
        },
        {
            "text": "dar a conocer su preocupaci\u00f3n porque se",
            "start": 341.71,
            "duration": 6.03
        },
        {
            "text": "piensa que van a utilizar a duarte para",
            "start": 345.28,
            "duration": 4.65
        },
        {
            "text": "que declaren en contra de nosotros y",
            "start": 347.74,
            "duration": 4.32
        },
        {
            "text": "unos d\u00edas antes de las elecciones va a",
            "start": 349.93,
            "duration": 4.23
        },
        {
            "text": "salir del arte a decir que le dio dinero",
            "start": 352.06,
            "duration": 5.04
        },
        {
            "text": "a morena no se preocupen por eso porque",
            "start": 354.16,
            "duration": 5.93
        },
        {
            "text": "no si esto no es verdad",
            "start": 357.1,
            "duration": 5.75
        },
        {
            "text": "nosotros no somos corruptos tengan",
            "start": 360.09,
            "duration": 7.14
        },
        {
            "text": "confianza nuestra protecci\u00f3n nuestro",
            "start": 362.85,
            "duration": 8.9
        },
        {
            "text": "escudo protector es la honestidad",
            "start": 367.23,
            "duration": 9.15
        },
        {
            "text": "entonces no hay nada que temer y ojal\u00e1 y",
            "start": 371.75,
            "duration": 6.87
        },
        {
            "text": "duarte",
            "start": 376.38,
            "duration": 2.24
        },
        {
            "text": "diga",
            "start": 379.5,
            "duration": 5.37
        },
        {
            "text": "como fue traicionado por pe\u00f1a",
            "start": 382.18,
            "duration": 5.27
        },
        {
            "text": "porque aparte \u00e9l entreg\u00f3 dinero para su",
            "start": 384.87,
            "duration": 8.48
        },
        {
            "text": "campa\u00f1a en el 2012 y luego pe\u00f1a se ali\u00f3",
            "start": 387.45,
            "duration": 9.79
        },
        {
            "text": "y\u00fanes linares del pan de felipe calder\u00f3n",
            "start": 393.35,
            "duration": 6.43
        },
        {
            "text": "y",
            "start": 397.24,
            "duration": 2.54
        },
        {
            "text": "pero",
            "start": 399.8,
            "duration": 5.82
        },
        {
            "text": "para establecer ese acuerdo de frenar de",
            "start": 402.35,
            "duration": 6.15
        },
        {
            "text": "detener tambi\u00e9n transitoriamente de",
            "start": 405.62,
            "duration": 5.54
        },
        {
            "text": "lograr",
            "start": 408.5,
            "duration": 2.66
        },
        {
            "text": "para siempre transitoriamente a morena",
            "start": 411.23,
            "duration": 6.75
        },
        {
            "text": "en veracruz y ahora de nuevo ah\u00ed est\u00e1 el",
            "start": 414.23,
            "duration": 7.47
        },
        {
            "text": "acuerdo para buscar frenar a morena en",
            "start": 417.98,
            "duration": 5.94
        },
        {
            "text": "el estado les vamos a ganar",
            "start": 421.7,
            "duration": 4.74
        },
        {
            "text": "y veracruz les vamos a ganar en el",
            "start": 423.92,
            "duration": 4.54
        },
        {
            "text": "estado de mexico y desde luego",
            "start": 426.44,
            "duration": 5.43
        },
        {
            "text": "le vamos a ganar el a\u00f1o pr\u00f3ximo",
            "start": 428.46,
            "duration": 6.77
        },
        {
            "text": "en el 18 la tercera es la vencida no",
            "start": 431.87,
            "duration": 6.75
        },
        {
            "text": "vamos a poder los de la mafia",
            "start": 435.23,
            "duration": 7.95
        },
        {
            "text": "del poder no vamos a poder con morir les",
            "start": 438.62,
            "duration": 5.909
        },
        {
            "text": "va a ganar",
            "start": 443.18,
            "duration": 5.73
        },
        {
            "text": "morena porque morena",
            "start": 444.529,
            "duration": 8.831
        },
        {
            "text": "es un referente moral va a ganar",
            "start": 448.91,
            "duration": 8.309
        },
        {
            "text": "la justicia al poder",
            "start": 453.36,
            "duration": 3.859
        }
    ],
    "transcription_text": " la semana santa fue como la semana de los curas de la pol\u00edtica mexicana el caso m\u00e1s sonado fue sin duda el de la detenci\u00f3n de parte del gobernador corrupto de veracruz la gente sabe porque estuvieron es yo pienso de dominio p\u00fablico de todas maneras es importante dar a conocer nuestro punto de vista nuestra versi\u00f3n pensamos igual que la gente que es una maniobra pol\u00edtica porque hay elecciones en puerta tanto en veracruz como mil estado de m\u00e9xico y est\u00e1n muy nerviosos est\u00e1 cayendo spri est\u00e1 cayendo el pan los dos partes que son los que est\u00e1n en picada y morena est\u00e1 creciendo mucho entonces y tomaron la decisi\u00f3n de detener en estos momentos a duarte para buscas en lo das a morir hay que tener en cuenta que y\u00fanes linares gobernador tambi\u00e9n corrupto de veracruz llev\u00f3 a declarar de que nosotros proteg\u00edamos a duarte porque duarte le daba dinero a morenico su prima de dinero a m\u00ed nada ha podido probar porque desde luego que no es cierto pero aplica la m\u00e1xima adelantada de la pol\u00edtica seg\u00fan la cual la calumnia cuando no mancha tista y ahora detienen a duarte en estos momentos y sale a declarar y\u00fanes el primero dice que ya cumpli\u00f3 con la detenci\u00f3n de suerte porque piensa que con eso se va a fortalecer \u00e9l y el pan en veracruz pero por cierto est\u00e1 apoyando a su hijo como candidato a presidente municipal del puerto de veracruz por el pan no les va a funcionar nada les sale tambi\u00e9n a decir y\u00fanes que felicitaba a pe\u00f1a nieto por la detenci\u00f3n de suerte pero lo m\u00e1s interesante es que declara ayer josefina v\u00e1zquez mota que ahora que le tienen a duarte debe d declarado arte sobre el dinero que entregaba a morena es decir lleva ese prop\u00f3sito de perjudicar a morena de enlodar a morir con la detenci\u00f3n de \u00e9dgar nosotros no tenemos ninguna relaci\u00f3n con duarte ni con ning\u00fan corrupto y ella no tiene las josefina v\u00e1squez mota moral ella recibi\u00f3 y est\u00e1 probado eso s\u00ed est\u00e1 demostrado no la calumnia de que duarte le da dinero a morena lo que s\u00ed se comprob\u00f3 es que despu\u00e9s de la elecci\u00f3n del 2012 que ya fue candidata sus defina las que no est\u00e1 presidenta de la rep\u00fablica por el pan y pasan las elecciones del 2012 y desaparece y se sabe qu\u00e9 pe\u00f1a nieto autor y son despu\u00e9s de la elecci\u00f3n del 2012 que le entregar\u00e1n a josefina v\u00e1zquez mota del presupuesto p\u00fablico m\u00e1s de mil millones de pesos para su fundaci\u00f3n supuestamente para apoyar a migrantes nunca ha demostrado que utiliz\u00f3 lo cierto aunque suene fuerte y luego con respeto es que se vendi\u00f3 pero s\u00f3lo es ellos tienen arreglo la c\u00fapula por eso hablo del prian y siempre he sostenido que son lo mismo iguales de los del pri los del pan de arriba hace dos meses y dio a conocer en una columna del peri\u00f3dico universal que se reunieron a medianoche anaya presidente del pan un aprendiz de mafioso con pe\u00f1a nieto tambi\u00e9n de la noche los pinos y hay la versi\u00f3n de que a esa reuni\u00f3n asisti\u00f3 tambi\u00e9n y ah\u00ed tomaron el acuerdo de ir juntos de facto de hecho en el estado de m\u00e9xico con dos candidaturas las dem\u00e1s del pri y la de josefina v\u00e1squez mota para enfrentar a morena ahora que morena est\u00e1 arriba en veracruz arriba en el estado de m\u00e9xico est\u00e1n muy desesperados y est\u00e1n con esta treta buscando frenar la morena no lo van a lograr ahora que tienen a duarte amigos nuestros de las redes sociales empiezan a preocuparse dar a conocer su preocupaci\u00f3n porque se piensa que van a utilizar a duarte para que declaren en contra de nosotros y unos d\u00edas antes de las elecciones va a salir del arte a decir que le dio dinero a morena no se preocupen por eso porque no si esto no es verdad nosotros no somos corruptos tengan confianza nuestra protecci\u00f3n nuestro escudo protector es la honestidad entonces no hay nada que temer y ojal\u00e1 y duarte diga como fue traicionado por pe\u00f1a porque aparte \u00e9l entreg\u00f3 dinero para su campa\u00f1a en el 2012 y luego pe\u00f1a se ali\u00f3 y\u00fanes linares del pan de felipe calder\u00f3n y pero para establecer ese acuerdo de frenar de detener tambi\u00e9n transitoriamente de lograr para siempre transitoriamente a morena en veracruz y ahora de nuevo ah\u00ed est\u00e1 el acuerdo para buscar frenar a morena en el estado les vamos a ganar y veracruz les vamos a ganar en el estado de mexico y desde luego le vamos a ganar el a\u00f1o pr\u00f3ximo en el 18 la tercera es la vencida no vamos a poder los de la mafia del poder no vamos a poder con morir les va a ganar morena porque morena es un referente moral va a ganar la justicia al poder ",
    "transcription_source": "YouTube auto-generated captions",
    "playlist_id": null,
    "playlist_title": null,
    "published_time_text": "6 years ago",
    "retrieved_time": "2023-09-07 19:51:19.936487"
}